{
  "record": "27-55",
  "coach": "Mike D'Antoni",
  "roster": [
    {
      "No.": 6,
      "Player": "Kent Bazemore",
      "Pos": "SG",
      "Ht": "6-5",
      "Wt": 201,
      "Birth Date": "July 1 1989",
      "": "us",
      "Exp": 1,
      "College": "Old Dominion University"
    },
    {
      "No.": 5,
      "Player": "Steve Blake",
      "Pos": "PG",
      "Ht": "6-3",
      "Wt": 172,
      "Birth Date": "February 26 1980",
      "": "us",
      "Exp": 10,
      "College": "University of Maryland"
    },
    {
      "No.": 2,
      "Player": "MarShon Brooks",
      "Pos": "SG",
      "Ht": "6-5",
      "Wt": 200,
      "Birth Date": "January 26 1989",
      "": "us",
      "Exp": 2,
      "College": "Providence College"
    },
    {
      "No.": 24,
      "Player": "Kobe Bryant",
      "Pos": "SG",
      "Ht": "6-6",
      "Wt": 212,
      "Birth Date": "August 23 1978",
      "": "us",
      "Exp": 17,
      "College": ""
    },
    {
      "No.": 1,
      "Player": "Jordan Farmar",
      "Pos": "PG",
      "Ht": "6-2",
      "Wt": 180,
      "Birth Date": "November 30 1986",
      "": "us",
      "Exp": 6,
      "College": "University of California Los Angeles"
    },
    {
      "No.": 16,
      "Player": "Pau Gasol",
      "Pos": "C",
      "Ht": "7-0",
      "Wt": 250,
      "Birth Date": "July 6 1980",
      "": "es",
      "Exp": 12,
      "College": ""
    },
    {
      "No.": 2,
      "Player": "Elias Harris",
      "Pos": "SF",
      "Ht": "6-8",
      "Wt": 239,
      "Birth Date": "July 6 1989",
      "": "de",
      "Exp": "R",
      "College": "Gonzaga University"
    },
    {
      "No.": 3,
      "Player": "Manny Harris",
      "Pos": "SG",
      "Ht": "6-5",
      "Wt": 185,
      "Birth Date": "September 21 1989",
      "": "us",
      "Exp": 2,
      "College": "University of Michigan"
    },
    {
      "No.": 7,
      "Player": "Xavier Henry",
      "Pos": "SF",
      "Ht": "6-6",
      "Wt": 220,
      "Birth Date": "March 15 1991",
      "": "be",
      "Exp": 3,
      "College": "University of Kansas"
    },
    {
      "No.": 27,
      "Player": "Jordan Hill",
      "Pos": "PF",
      "Ht": "6-10",
      "Wt": 235,
      "Birth Date": "July 27 1987",
      "": "us",
      "Exp": 4,
      "College": "University of Arizona"
    },
    {
      "No.": 11,
      "Player": "Wesley Johnson",
      "Pos": "SF",
      "Ht": "6-7",
      "Wt": 215,
      "Birth Date": "July 11 1987",
      "": "us",
      "Exp": 3,
      "College": "Iowa State University Syracuse University"
    },
    {
      "No.": 9,
      "Player": "Chris Kaman",
      "Pos": "C",
      "Ht": "7-0",
      "Wt": 265,
      "Birth Date": "April 28 1982",
      "": "us",
      "Exp": 10,
      "College": "Central Michigan University"
    },
    {
      "No.": 4,
      "Player": "Ryan Kelly",
      "Pos": "PF",
      "Ht": "6-11",
      "Wt": 230,
      "Birth Date": "April 9 1991",
      "": "us",
      "Exp": "R",
      "College": "Duke University"
    },
    {
      "No.": 12,
      "Player": "Kendall Marshall",
      "Pos": "PG",
      "Ht": "6-4",
      "Wt": 200,
      "Birth Date": "August 19 1991",
      "": "us",
      "Exp": 1,
      "College": "University of North Carolina"
    },
    {
      "No.": 20,
      "Player": "Jodie Meeks",
      "Pos": "SG",
      "Ht": "6-4",
      "Wt": 210,
      "Birth Date": "August 21 1987",
      "": "us",
      "Exp": 4,
      "College": "University of Kentucky"
    },
    {
      "No.": 10,
      "Player": "Steve Nash",
      "Pos": "PG",
      "Ht": "6-3",
      "Wt": 195,
      "Birth Date": "February 7 1974",
      "": "za",
      "Exp": 17,
      "College": "Santa Clara University"
    },
    {
      "No.": 50,
      "Player": "Robert Sacre",
      "Pos": "C",
      "Ht": "7-0",
      "Wt": 270,
      "Birth Date": "June 6 1989",
      "": "us",
      "Exp": 1,
      "College": "Gonzaga University"
    },
    {
      "No.": 3,
      "Player": "Shawne Williams",
      "Pos": "PF",
      "Ht": "6-9",
      "Wt": 225,
      "Birth Date": "February 16 1986",
      "": "us",
      "Exp": 5,
      "College": "University of Memphis"
    },
    {
      "No.": 0,
      "Player": "Nick Young",
      "Pos": "SG",
      "Ht": "6-7",
      "Wt": 210,
      "Birth Date": "June 1 1985",
      "": "us",
      "Exp": 6,
      "College": "University of Southern California"
    }
  ]
}
